jet_bridge_base/__init__.py
jet_bridge_base/automap.py
jet_bridge_base/configuration.py
jet_bridge_base/db.py
jet_bridge_base/encoders.py
jet_bridge_base/logger.py
jet_bridge_base/media_cache.py
jet_bridge_base/messages.py
jet_bridge_base/permissions.py
jet_bridge_base/request.py
jet_bridge_base/router.py
jet_bridge_base/sentry.py
jet_bridge_base/settings.py
jet_bridge_base/ssh_tunnel.py
jet_bridge_base/status.py
jet_bridge_base/store.py
jet_bridge_base/__pycache__/__init__.cpython-313.pyc
jet_bridge_base/__pycache__/__init__.cpython-36.pyc
jet_bridge_base/__pycache__/automap.cpython-36.pyc
jet_bridge_base/__pycache__/configuration.cpython-36.pyc
jet_bridge_base/__pycache__/db.cpython-36.pyc
jet_bridge_base/__pycache__/encoders.cpython-36.pyc
jet_bridge_base/__pycache__/logger.cpython-313.pyc
jet_bridge_base/__pycache__/logger.cpython-36.pyc
jet_bridge_base/__pycache__/media_cache.cpython-36.pyc
jet_bridge_base/__pycache__/messages.cpython-36.pyc
jet_bridge_base/__pycache__/permissions.cpython-36.pyc
jet_bridge_base/__pycache__/request.cpython-36.pyc
jet_bridge_base/__pycache__/router.cpython-36.pyc
jet_bridge_base/__pycache__/sentry.cpython-36.pyc
jet_bridge_base/__pycache__/settings.cpython-313.pyc
jet_bridge_base/__pycache__/settings.cpython-36.pyc
jet_bridge_base/__pycache__/ssh_tunnel.cpython-36.pyc
jet_bridge_base/__pycache__/status.cpython-36.pyc
jet_bridge_base/__pycache__/store.cpython-36.pyc
jet_bridge_base/commands/__init__.py
jet_bridge_base/commands/check_token.py
jet_bridge_base/commands/__pycache__/__init__.cpython-36.pyc
jet_bridge_base/commands/__pycache__/check_token.cpython-36.pyc
jet_bridge_base/db_types/__init__.py
jet_bridge_base/db_types/common.py
jet_bridge_base/db_types/db.py
jet_bridge_base/db_types/discover.py
jet_bridge_base/db_types/metadata_file.py
jet_bridge_base/db_types/queryset.py
jet_bridge_base/db_types/timezones.py
jet_bridge_base/db_types/__pycache__/__init__.cpython-36.pyc
jet_bridge_base-1.12.7.dist-info/LICENSE
jet_bridge_base-1.12.7.dist-info/METADATA
jet_bridge_base-1.12.7.dist-info/WHEEL
jet_bridge_base-1.12.7.dist-info/top_level.txt
jet_bridge_base-1.12.7.dist-info/RECORD
