Metadata-Version: 2.1
Name: jet-bridge-base
Version: 1.12.7
Summary: UNKNOWN
Home-page: https://github.com/jet-admin/jet-bridge-base
Author: Denis Kildishev
Author-email: support@jetadmin.io
License: MIT
Platform: UNKNOWN
Requires-Dist: sqlalchemy (<2.0)
Requires-Dist: pymongo[srv] (==4.1.1)
Requires-Dist: six
Requires-Dist: requests
Requires-Dist: Pillow
Requires-Dist: dateparser
Requires-Dist: python-dateutil
Requires-Dist: psutil
Requires-Dist: social-auth-core
Requires-Dist: prompt-toolkit (==2.0.9)
Requires-Dist: graphene (<3.0)
